daily_tweeter/__init__.py
daily_tweeter/client.py
daily_tweeter/cmd.py
daily_tweeter/config.py
daily_tweeter/posts.py
daily_tweeter/publish.py
daily_tweeter/schedule.py
daily_tweeter-0.1.0.dist-info/DESCRIPTION.rst
daily_tweeter-0.1.0.dist-info/METADATA
daily_tweeter-0.1.0.dist-info/RECORD
daily_tweeter-0.1.0.dist-info/WHEEL
daily_tweeter-0.1.0.dist-info/entry_points.txt
daily_tweeter-0.1.0.dist-info/metadata.json
daily_tweeter-0.1.0.dist-info/pbr.json
daily_tweeter-0.1.0.dist-info/top_level.txt
